myterial/__init__.py
myterial/codes.py
myterial/lookup.py
myterial/show.py
myterial/utils.py
myterial-1.2.1.dist-info/LICENSE
myterial-1.2.1.dist-info/METADATA
myterial-1.2.1.dist-info/WHEEL
myterial-1.2.1.dist-info/top_level.txt
myterial-1.2.1.dist-info/RECORD
